[
  {
    "Coffee Name": "Heart Eyes",
    "Roaster Name & Location": "Monogram Coffee — Calgary AB, Canada 🇨🇦",
    "Origin & Region": "",
    "More on Origin": "",
    "Altitude Range": "",
    "Variety & Process": "",
    "Cover": "https://images.squarespace-cdn.com/content/69af0cac1b048c64c0c2e18a/1773238311498-K9R7EVHWZHX55RPM1FTB/Heart-Eyes.png?content-type=image%2Fpng",
    "About the Coffee": "",
    "Roaster Recognition & Awards": "",
    "More from the Drawdown": "",
    "Publish": true,
    "Featured": false,
    "Created": "2026-03-13T15:53:00.000Z",
    "Last Updated": "2026-03-28T00:42:20.700Z"
  },
  {
    "Coffee Name": "HACHI - TANI (谷)",
    "Roaster Name & Location": "Native Coffee Company — Chiriqui, Panama 🇵🇦",
    "Origin & Region": "",
    "More on Origin": "(Guayabillas, Bolívar)",
    "Altitude Range": "",
    "Variety & Process": "",
    "Cover": "https://images.squarespace-cdn.com/content/69af0cac1b048c64c0c2e18a/1773241562982-IYGM6IE19AEOLQ9D78FQ/HACHI-TANI.png?content-type=image%2Fpng",
    "About the Coffee": "",
    "Roaster Recognition & Awards": "",
    "More from the Drawdown": "https://www.pillarandpress.studio/from-the-drawdown/hachi-tani-native-coffee-co",
    "Publish": true,
    "Featured": false,
    "Created": "2026-03-13T15:48:00.000Z",
    "Last Updated": "2026-03-28T00:42:20.810Z"
  },
  {
    "Coffee Name": "Finca La Patria",
    "Roaster Name & Location": "Rooftop Coffee Roasters — Fernie BC, Canada 🇨🇦",
    "Origin & Region": "",
    "More on Origin": "(Tapachula)",
    "Altitude Range": "Medium Altitude",
    "Variety & Process": "",
    "Cover": "https://images.squarespace-cdn.com/content/69af0cac1b048c64c0c2e18a/1773241846941-ISA898KK829YLX1WY7D4/Finca_La_Patria.png?content-type=image%2Fpng",
    "About the Coffee": "",
    "Roaster Recognition & Awards": "",
    "More from the Drawdown": "https://www.pillarandpress.studio/from-the-drawdown/heart-eyes-monogram-coffee",
    "Publish": true,
    "Featured": false,
    "Created": "2026-03-13T14:17:00.000Z",
    "Last Updated": "2026-03-28T00:42:20.810Z"
  }
]